kyapikeyserver/__init__.py
kyapikeyserver/init.py
kyapikeyserver/server.py
pyapikeyserver-0.0.1.dist-info/METADATA
pyapikeyserver-0.0.1.dist-info/WHEEL
pyapikeyserver-0.0.1.dist-info/top_level.txt
pyapikeyserver-0.0.1.dist-info/RECORD
