Metadata-Version: 2.4
Name: pyapikeyserver
Version: 0.0.1
Summary: Your project description
Author: "yu moqing"
Author-email: "yumoqing@gmail.com"
License: "MIT"
Requires-Dist: apppublic
Requires-Dist: sqlor
Requires-Dist: ahserver
